starlette_plus/__init__.py
starlette_plus/core.py
starlette_plus/limiter.py
starlette_plus/py.typed
starlette_plus/redis.py
starlette_plus/utils.py
starlette_plus/middleware/__init__.py
starlette_plus/middleware/ratelimiter.py
starlette_plus/middleware/sessions.py
starlette_plus/types_/core.py
starlette_plus/types_/limiter.py
Starlette_Plus-1.0.0.dist-info/LICENSE
Starlette_Plus-1.0.0.dist-info/METADATA
Starlette_Plus-1.0.0.dist-info/WHEEL
Starlette_Plus-1.0.0.dist-info/top_level.txt
Starlette_Plus-1.0.0.dist-info/RECORD
